second_library_src/__init__.py
second_library_src/main.py
second_library_src/py.typed
second_library_src-0.1.3.dist-info/METADATA
second_library_src-0.1.3.dist-info/WHEEL
second_library_src-0.1.3.dist-info/RECORD
