Metadata-Version: 2.4
Name: second-library-src
Version: 0.1.3
Summary: Add your description here
Author-email: Sakthivel Chellapparimanam <srcsak@amazon.com>
Requires-Python: >=3.13
Requires-Dist: boto3>=1.38.23
Requires-Dist: mcp[cli]>=1.9.1
